{
    "form_data": {
        "bankAccount": "",
        "bankBranch": "",
        "blob_url": "https://ezzydoc.blob.core.windows.net/docs/29810569.pdf?sv=2014-02-14&sr=b&sig=DTVm25Ff5B6ePHixZok0MhXTtXm%2B%2FjEXNx2x%2B1xgXSA%3D&st=2024-07-18T09%3A26%3A31Z&se=2124-07-18T09%3A31%3A31Z&sp=r",
        "charge": 0.0,
        "classification": 2,
        "form_data": {
            "abn": "",
            "additional_request": null,
            "approver": null,
            "approver_email": null,
            "bPayRef": null,
            "bPaycode": null,
            "bankAccount": null,
            "bankBranch": null,
            "bank_details": null,
            "changed": true,
            "charge": 0.0,
            "company_invoiced": "ABC COMPANY\r\n",
            "customField1": null,
            "customField2": null,
            "customField3": null,
            "customField4": null,
            "customValues": null,
            "delivery_to": null,
            "delivery_to_address": "ABC COMPANY\r\n2 ABC ROAD, WATERLOO, 2017\r\n",
            "description": null,
            "document_subtype": 1,
            "email": null,
            "email_to": null,
            "expense_claim": null,
            "from_email": null,
            "glcode_option": null,
            "glcode_text": null,
            "invoiceDate": "/Date(1720742400000+0000)/",
            "invoiceNumber": "17-34",
            "invoice_to": null,
            "invoice_to_address": "ABC COMPANY\r\n2 ABC ROAD, WATERLOO, 2017\r\n",
            "location": null,
            "purchaseOrder": "",
            "require_bank_details": false,
            "require_email": false,
            "supplier": "UNKNOWN_CONTACT",
            "supplier_address": "ABC COMPANY\r\n2 ABC ROAD, WATERLOO, 2017\r\n",
            "supplier_id": null,
            "tax": 2.18,
            "total": 24.0,
            "tracking": null,
            "tracking_option": null
        },
        "gst_total": 2.18,
        "invoice_number": "17-34",
        "locale": 0,
        "pdf_url": "https://ezzydoc.blob.core.windows.net/docs/29810569_link.pdf?sv=2014-02-14&sr=b&sig=w%2BsER67i7Jz9Wz4PvtjxoBWeNaQitVcxUjy%2BLvaz4go%3D&st=2024-07-18T09%3A26%3A31Z&se=2124-07-18T09%3A31%3A31Z&sp=r",
        "service_status": {
            "invoice_id": 0,
            "message": "",
            "status": 0
        },
        "supplier_name": "UNKNOWN_CONTACT",
        "thumb_url": "https://ezzydoc.blob.core.windows.net/docs/thumb_29810569.png?sv=2014-02-14&sr=b&sig=ZLV381AIPPMYss4BhYRn4XI5NlMagKE4WjLe0XYmw0s%3D&st=2024-07-18T09%3A26%3A31Z&se=2124-07-18T09%3A31%3A31Z&sp=r",
        "total": 24.0
    },
    "invoiceForm": {
        "invoiceForm": {
            "ABNnumber": "",
            "RefNumber": "",
            "bankAccount": "",
            "bankBranch": "",
            "bankReference": "",
            "chargeTotal": 0.0,
            "discountTotal": 0.0,
            "docType": 1,
            "gstTotal": 2.18,
            "invoiceDate": "/Date(1720742400000+0000)/",
            "invoiceNumber": "17-34",
            "invoiceTotal": 24.0,
            "paymentDate": "/Date(1721952000000+0000)/",
            "purchaseOrder": "",
            "subTotal": 21.82,
            "supplierName": "UNKNOWN_CONTACT",
            "tag": "NEW FOLDER"
        },
        "list": [
            null,
            {
                "header": 0,
                "height": 0,
                "page": -1,
                "text": "",
                "width": 0,
                "x": 0,
                "y": 0
            },
            {
                "header": 0,
                "height": 0,
                "page": -1,
                "text": "",
                "width": 0,
                "x": 0,
                "y": 0
            },
            {
                "header": 0,
                "height": 43,
                "page": 0,
                "text": "2024-07-12",
                "width": 235,
                "x": 2075,
                "y": 572
            },
            {
                "header": 0,
                "height": 64,
                "page": 0,
                "text": "17-34",
                "width": 199,
                "x": 1397,
                "y": 807
            },
            {
                "header": 0,
                "height": 0,
                "page": -1,
                "text": "",
                "width": 0,
                "x": 0,
                "y": 0
            },
            {
                "header": 0,
                "height": 43,
                "page": 0,
                "text": "21.82",
                "width": 119,
                "x": 2202,
                "y": 1488
            },
            {
                "header": 0,
                "height": 42,
                "page": 0,
                "text": "2.18",
                "width": 92,
                "x": 2229,
                "y": 1550
            },
            {
                "header": 0,
                "height": 0,
                "page": -1,
                "text": "",
                "width": 0,
                "x": 0,
                "y": 0
            },
            {
                "header": 0,
                "height": 43,
                "page": 0,
                "text": "24.00",
                "width": 131,
                "x": 2190,
                "y": 1611
            },
            {
                "header": 0,
                "height": 0,
                "page": 0,
                "text": "",
                "width": 0,
                "x": 0,
                "y": 0
            },
            {
                "header": 0,
                "height": 43,
                "page": 0,
                "text": "2024-07-26",
                "width": 235,
                "x": 2075,
                "y": 628
            },
            {
                "header": 0,
                "height": 0,
                "page": -1,
                "text": "",
                "width": 0,
                "x": 0,
                "y": 0
            },
            null
        ],
        "service_status": {
            "invoice_id": 29810569,
            "message": "",
            "status": 0
        },
        "table": [
            {
                "article_code": "",
                "description": "a burger\nTWENTY FOUR AUD AND 00 CENTS",
                "gl_code": "",
                "gst": 2.182,
                "quantity": 1,
                "row_height": 178,
                "row_page": 0,
                "row_y": 1194,
                "tax_code": "(10%)",
                "total": 21.82,
                "total_excl": 0,
                "total_incl": 0,
                "tracking": "",
                "unit_measure": "",
                "unit_price": 21.82
            }
        ]
    },
    "table": {
        "invoiceForm": {
            "ABNnumber": "",
            "RefNumber": "",
            "bankAccount": "",
            "bankBranch": "",
            "bankReference": "",
            "chargeTotal": 0.0,
            "discountTotal": 0.0,
            "docType": 1,
            "gstTotal": 2.18,
            "invoiceDate": "/Date(1720742400000+0000)/",
            "invoiceNumber": "17-34",
            "invoiceTotal": 24.0,
            "paymentDate": "/Date(1721952000000+0000)/",
            "purchaseOrder": "",
            "subTotal": 21.82,
            "supplierName": "UNKNOWN_CONTACT",
            "tag": "NEW FOLDER"
        },
        "list": [
            null,
            {
                "header": 0,
                "height": 0,
                "page": -1,
                "text": "",
                "width": 0,
                "x": 0,
                "y": 0
            },
            {
                "header": 0,
                "height": 0,
                "page": -1,
                "text": "",
                "width": 0,
                "x": 0,
                "y": 0
            },
            {
                "header": 0,
                "height": 43,
                "page": 0,
                "text": "2024-07-12",
                "width": 235,
                "x": 2075,
                "y": 572
            },
            {
                "header": 0,
                "height": 64,
                "page": 0,
                "text": "17-34",
                "width": 199,
                "x": 1397,
                "y": 807
            },
            {
                "header": 0,
                "height": 0,
                "page": -1,
                "text": "",
                "width": 0,
                "x": 0,
                "y": 0
            },
            {
                "header": 0,
                "height": 43,
                "page": 0,
                "text": "21.82",
                "width": 119,
                "x": 2202,
                "y": 1488
            },
            {
                "header": 0,
                "height": 42,
                "page": 0,
                "text": "2.18",
                "width": 92,
                "x": 2229,
                "y": 1550
            },
            {
                "header": 0,
                "height": 0,
                "page": -1,
                "text": "",
                "width": 0,
                "x": 0,
                "y": 0
            },
            {
                "header": 0,
                "height": 43,
                "page": 0,
                "text": "24.00",
                "width": 131,
                "x": 2190,
                "y": 1611
            },
            {
                "header": 0,
                "height": 0,
                "page": 0,
                "text": "",
                "width": 0,
                "x": 0,
                "y": 0
            },
            {
                "header": 0,
                "height": 43,
                "page": 0,
                "text": "2024-07-26",
                "width": 235,
                "x": 2075,
                "y": 628
            },
            {
                "header": 0,
                "height": 0,
                "page": -1,
                "text": "",
                "width": 0,
                "x": 0,
                "y": 0
            },
            null
        ],
        "service_status": {
            "invoice_id": 29810569,
            "message": "",
            "status": 0
        },
        "table": [
            {
                "article_code": "",
                "description": "a burger\nTWENTY FOUR AUD AND 00 CENTS",
                "gl_code": "",
                "gst": 2.182,
                "quantity": 1,
                "row_height": 178,
                "row_page": 0,
                "row_y": 1194,
                "tax_code": "(10%)",
                "total": 21.82,
                "total_excl": 0,
                "total_incl": 0,
                "tracking": "",
                "unit_measure": "",
                "unit_price": 21.82
            }
        ]
    }
}